[
    {
        "id": 17898061243225261,
        "created_at": 1534500436,
        "text": "\ud83e\udd23\ud83e\udd23 \u0111\u1ec7t",
        "owner": {
            "id": "4297711027",
            "is_verified": false,
            "profile_pic_url": "https://instagram.fhan2-3.fna.fbcdn.net/v/t51.2885-19/s150x150/15538177_131195937373514_434761221338562560_a.jpg?_nc_ht=instagram.fhan2-3.fna.fbcdn.net&_nc_ohc=wM8Vbxilb7UAX-DDoD-&oh=649675e98d8e1b2e369e7e82cbbf96e4&oe=5F80F000",
            "username": "bithongmacdanh"
        },
        "likes_count": 0,
        "answers": [
            {
                "id": 17910519898202341,
                "created_at": 1534501305,
                "text": "@bithongmacdanh end r :(( ki\u1ebfm ti\u1ec1n th\u00f4i @@",
                "owner": {
                    "id": "5706095553",
                    "is_verified": false,
                    "profile_pic_url": "https://instagram.fhan2-3.fna.fbcdn.net/v/t51.2885-19/s150x150/19765044_1580023805354704_919374450204344320_a.jpg?_nc_ht=instagram.fhan2-3.fna.fbcdn.net&_nc_ohc=x5ru1Evv79YAX81W42G&oh=768403ba002dd81df7e4633b30d6e613&oe=5F8197FE",
                    "username": "nghiahsgs"
                },
                "likes_count": 0
            }
        ]
    },
    {
        "id": 17972786332045003,
        "created_at": 1534473701,
        "text": "th\u1eadt l\u00e0 ng\u00f4l l\u00f9",
        "owner": {
            "id": "3993532879",
            "is_verified": false,
            "profile_pic_url": "https://instagram.fhan2-3.fna.fbcdn.net/v/t51.2885-19/s150x150/74670554_1438488216306801_6038255553208123392_n.jpg?_nc_ht=instagram.fhan2-3.fna.fbcdn.net&_nc_ohc=25-p6W_OqMYAX-ZkE69&oh=7c7ffb84b95b84ad678898df8180bb90&oe=5F83557E",
            "username": "baoanh_97"
        },
        "likes_count": 0,
        "answers": []
    }
]